mcp_caiyun_weather/__init__.py
mcp_caiyun_weather/server.py
mseep_mcp_caiyun_weather-0.1.2.dist-info/licenses/LICENSE
mseep_mcp_caiyun_weather-0.1.2.dist-info/METADATA
mseep_mcp_caiyun_weather-0.1.2.dist-info/WHEEL
mseep_mcp_caiyun_weather-0.1.2.dist-info/entry_points.txt
mseep_mcp_caiyun_weather-0.1.2.dist-info/top_level.txt
mseep_mcp_caiyun_weather-0.1.2.dist-info/RECORD
