Metadata-Version: 2.4
Name: mseep-mcp-caiyun-weather
Version: 0.1.2
Summary: Caiyun Weather MCP Server
Author-email: mseep <support@skydeck.ai>
Maintainer-email: adamwen <adamwen829@gmail.com>, tssujt <xujiawei@caiyunapp.com>, caiyunapp <oss@caiyunapp.com>
License: MIT License
Project-URL: Homepage, https://github.com/caiyunapp/mcp-caiyun-weather
Project-URL: Issues, https://github.com/caiyunapp/mcp-caiyun-weather/issues
Keywords: MCP,Weather
Requires-Python: >=3.12
License-File: LICENSE
Requires-Dist: httpx>=0.28.1
Requires-Dist: mcp[cli]>=1.5.0
Requires-Dist: pydantic>=2.10.6
Dynamic: license-file
